imantodes/__init__.py
imantodes/app.py
imantodes/event.py
imantodes/vecmat.py
imantodes-0.0.3.dist-info/licenses/LICENSE
imantodes-0.0.3.dist-info/METADATA
imantodes-0.0.3.dist-info/WHEEL
imantodes-0.0.3.dist-info/top_level.txt
imantodes-0.0.3.dist-info/RECORD
