Metadata-Version: 2.4
Name: imantodes
Version: 0.0.3
Summary: lightweight Python code for making interactive scivis apps
Author-email: Gordon Kindlmann <glk@uchicago.edu>
License-Expression: LGPL-3.0-only
Project-URL: Homepage, https://gitlab.com/gkindlmann-group/imantodes
Keywords: interactive,visualization,scivis
Classifier: Development Status :: 2 - Pre-Alpha
Classifier: Intended Audience :: Developers
Classifier: Intended Audience :: Science/Research
Classifier: Topic :: Scientific/Engineering :: Visualization
Classifier: Programming Language :: Python :: 3
Classifier: Programming Language :: Python :: 3.12
Classifier: Programming Language :: Python :: 3.13
Requires-Python: >=3.12
License-File: LICENSE
Requires-Dist: cffi>=1.16
Requires-Dist: frozendict>=2.4
Requires-Dist: pyside6>=6.8
Dynamic: license-file
